{
  "poules": [
    {
      "id": Groupe 1,
      "joueurs": [
        {
          "name": "François RO",
          "pts": 20
        },
        {
          "name": "Frédéric A",
          "pts": 12
        },
        {
          "name": "Laurent",
          "pts": 8
        },
        {
          "name": "Romain",
          "pts": 4
        }
      ]
    },
    {
      "id": 2,
      "joueurs": [
        {
          "name": "Mathis",
          "pts": 14
        },
        {
          "name": "Titouan",
          "pts": 14
        },
        {
          "name": "Nicolas",
          "pts": 11
        },
        {
          "name": "Maxime",
          "pts": 5
        }
      ]
    },
    {
      "id": 3,
      "joueurs": [
        {
          "name": "Raphaël",
          "pts": 18
        },
        {
          "name": "Mickael",
          "pts": 13
        },
        {
          "name": "Vincent",
          "pts": 7
        },
        {
          "name": "Bertrand",
          "pts": 6
        }
      ]
    },
    {
      "id": 4,
      "joueurs": [
        {
          "name": "Antoine M",
          "pts": 16
        },
        {
          "name": "Freddy",
          "pts": 16
        },
        {
          "name": "Benoît",
          "pts": 6
        },
        {
          "name": "Jérôme",
          "pts": 6
        }
      ]
    },
    {
      "id": 5,
      "joueurs": [
        {
          "name": "Anthony",
          "pts": 17
        },
        {
          "name": "Gilles",
          "pts": 12
        },
        {
          "name": "François RE",
          "pts": 11
        },
        {
          "name": "Jacky",
          "pts": 4
        }
      ]
    },
    {
      "id": 6,
      "joueurs": [
        {
          "name": "David",
          "pts": 18
        },
        {
          "name": "Jeanne",
          "pts": 14
        },
        {
          "name": "Frédéric G",
          "pts": 8
        },
        {
          "name": "Antoine C",
          "pts": 4
        }
      ]
    },
    {
      "id": 7,
      "joueurs": [
        {
          "name": "Benjamin",
          "pts": 16
        },
        {
          "name": "Cem",
          "pts": 16
        },
        {
          "name": "Christophe",
          "pts": 8
        },
        {
          "name": "Maël",
          "pts": 4
        }
      ]
    }
  ],
  "phase2": [],
  "quarts": [],
  "demis": [],
  "finale": [],
  "classement": []
}
